py_uconnect/__init__.py
py_uconnect/api.py
py_uconnect/brands.py
py_uconnect/client.py
py_uconnect/command.py
py_uconnect-0.3.11.dist-info/licenses/LICENSE
py_uconnect-0.3.11.dist-info/METADATA
py_uconnect-0.3.11.dist-info/WHEEL
py_uconnect-0.3.11.dist-info/top_level.txt
py_uconnect-0.3.11.dist-info/RECORD
