Metadata-Version: 2.4
Name: py-uconnect
Version: 0.3.11
Summary: Python API Client for FCA/Stellantis cars
Home-page: https://github.com/hass-uconnect/py-uconnect
Author: Olga Novgorodova
Author-email: olga@novg.net
License: Apache license
Keywords: fiat,jeep,dodge,ram,alfa,romeo,maserati,chrysler,api,cloud
Classifier: Development Status :: 5 - Production/Stable
Classifier: Intended Audience :: Developers
Classifier: License :: OSI Approved :: Apache Software License
Classifier: Natural Language :: English
Classifier: Programming Language :: Python :: 3.10
Requires-Python: >=3.10
License-File: LICENSE
Requires-Dist: boto3>=1.35.96
Requires-Dist: requests>=2.32.3
Requires-Dist: requests-auth-aws-sigv4>=0.7
Requires-Dist: dataclasses_json>=0.6.7
Dynamic: author
Dynamic: author-email
Dynamic: classifier
Dynamic: description
Dynamic: description-content-type
Dynamic: home-page
Dynamic: keywords
Dynamic: license
Dynamic: license-file
Dynamic: requires-dist
Dynamic: requires-python
Dynamic: summary
